dictim/__init__.py
dictim/__version__.py
dictim/dictim.py
dictim-0.2.3.dist-info/LICENSE
dictim-0.2.3.dist-info/LICENSE.txt
dictim-0.2.3.dist-info/METADATA
dictim-0.2.3.dist-info/WHEEL
dictim-0.2.3.dist-info/top_level.txt
dictim-0.2.3.dist-info/RECORD
