Metadata-Version: 2.1
Name: dictim
Version: 0.2.3
Summary: case insensitive dict for modern python
Home-page: https://github.com/jamesabel/dictim
Download-URL: https://github.com/jamesabel/dictim
Author: abel
Author-email: j@abel.co
License: MIT License
Keywords: dict,case,insensitive
License-File: LICENSE
License-File: LICENSE.txt
